CLA.txt
CONTRIBUTE.md
LICENSE.txt
MANIFEST.in
README.rst
netscalertool.conf.example
python-netscalertool.spec
requirements.txt
setup.py
netscaler_tool.egg-info/PKG-INFO
netscaler_tool.egg-info/SOURCES.txt
netscaler_tool.egg-info/dependency_links.txt
netscaler_tool.egg-info/entry_points.txt
netscaler_tool.egg-info/requires.txt
netscaler_tool.egg-info/top_level.txt
netscalertool/__init__.py
netscalertool/netscalerapi.py
netscalertool/netscalertool.py
netscalertool/utils.py